core/__init__.py
core/acl.py
core/lacp.py
core/main.py
core/speed.py
core/state.py
core/status.py
core/utils.py
netswitcher-0.2.1.dist-info/METADATA
netswitcher-0.2.1.dist-info/WHEEL
netswitcher-0.2.1.dist-info/entry_points.txt
netswitcher-0.2.1.dist-info/RECORD
