Metadata-Version: 2.1
Name: netswitcher
Version: 0.2.1
Summary: 
Author: Fearkin
Author-email: aloneWorker@yandex.ru
Requires-Python: >=3.8,<4.0
Classifier: Programming Language :: Python :: 3
Classifier: Programming Language :: Python :: 3.8
Classifier: Programming Language :: Python :: 3.9
Classifier: Programming Language :: Python :: 3.10
Classifier: Programming Language :: Python :: 3.11
Requires-Dist: netmiko (>=4.3.0,<5.0.0)
Requires-Dist: typer-slim (>=0.12.3,<0.13.0)
